membrain_seg/__init__.py
membrain_seg/annotations/__init__.py
membrain_seg/annotations/cli.py
membrain_seg/annotations/extract_patch_cli.py
membrain_seg/annotations/extract_patches.py
membrain_seg/annotations/merge_corrections.py
membrain_seg/annotations/merge_corrections_cli.py
membrain_seg/benchmark/__init__.py
membrain_seg/benchmark/compute_stats.py
membrain_seg/benchmark/metrics.py
membrain_seg/segmentation/__init__.py
membrain_seg/segmentation/connected_components.py
membrain_seg/segmentation/finetune.py
membrain_seg/segmentation/parse_utils.py
membrain_seg/segmentation/segment.py
membrain_seg/segmentation/skeletonize.py
membrain_seg/segmentation/train.py
membrain_seg/segmentation/cli/__init__.py
membrain_seg/segmentation/cli/cli.py
membrain_seg/segmentation/cli/fine_tune_cli.py
membrain_seg/segmentation/cli/segment_cli.py
membrain_seg/segmentation/cli/ske_cli.py
membrain_seg/segmentation/cli/train_cli.py
membrain_seg/segmentation/dataloading/__init__.py
membrain_seg/segmentation/dataloading/data_utils.py
membrain_seg/segmentation/dataloading/memseg_augmentation.py
membrain_seg/segmentation/dataloading/memseg_dataset.py
membrain_seg/segmentation/dataloading/memseg_pl_datamodule.py
membrain_seg/segmentation/dataloading/transforms.py
membrain_seg/segmentation/networks/__init__.py
membrain_seg/segmentation/networks/inference_unet.py
membrain_seg/segmentation/networks/unet.py
membrain_seg/segmentation/skeletonization/__init__.py
membrain_seg/segmentation/skeletonization/diff3d.py
membrain_seg/segmentation/skeletonization/eig3d.py
membrain_seg/segmentation/skeletonization/nonmaxsup.py
membrain_seg/segmentation/training/__init__.py
membrain_seg/segmentation/training/metric_utils.py
membrain_seg/segmentation/training/optim_utils.py
membrain_seg/segmentation/training/surface_dice.py
membrain_seg/segmentation/training/training_param_summary.py
membrain_seg/tomo_download/__init__.py
membrain_seg/tomo_preprocessing/README.md
membrain_seg/tomo_preprocessing/__init__.py
membrain_seg-0.0.8.dist-info/METADATA
membrain_seg-0.0.8.dist-info/WHEEL
membrain_seg-0.0.8.dist-info/entry_points.txt
membrain_seg-0.0.8.dist-info/licenses/LICENSE
membrain_seg-0.0.8.dist-info/RECORD
